consistency/__init__.py
consistency/consistency.py
consistency/loss.py
consistency/pipeline.py
consistency-0.3.2.dist-info/LICENSE
consistency-0.3.2.dist-info/METADATA
consistency-0.3.2.dist-info/WHEEL
consistency-0.3.2.dist-info/top_level.txt
consistency-0.3.2.dist-info/RECORD
